societyai/__doc__.py
societyai/__init__.py
societyai/helpers.py
societyai-0.1.3.dist-info/LICENSE
societyai-0.1.3.dist-info/METADATA
societyai-0.1.3.dist-info/NOTICE.txt
societyai-0.1.3.dist-info/WHEEL
societyai-0.1.3.dist-info/top_level.txt
societyai-0.1.3.dist-info/RECORD
